metriql2lookml/__init__.py
metriql2lookml/generator.py
metriql2lookml/models.py
metriql_lookml-0.3.data/scripts/metriql-lookml
metriql_lookml-0.3.dist-info/LICENSE
metriql_lookml-0.3.dist-info/METADATA
metriql_lookml-0.3.dist-info/WHEEL
metriql_lookml-0.3.dist-info/top_level.txt
metriql_lookml-0.3.dist-info/RECORD
