Metadata-Version: 2.1
Name: metriql-lookml
Version: 0.3
Summary: metriql Looker integration
Home-page: https://github.com/metriql/lookml-generator
Author: Umar Majeed
Author-email: emre@rakam.io
License: MIT License
Platform: UNKNOWN
Classifier: Development Status :: 3 - Alpha
Classifier: Intended Audience :: Developers
Classifier: License :: OSI Approved :: MIT License
Classifier: Operating System :: OS Independent
Classifier: Programming Language :: Python
Classifier: Programming Language :: Python :: 3 :: Only
Classifier: Programming Language :: Python :: 3.6
Classifier: Programming Language :: Python :: 3.7
Classifier: Topic :: Software Development :: Libraries
Classifier: Topic :: Software Development :: Libraries :: Python Modules
License-File: LICENSE
Requires-Dist: pydantic
Requires-Dist: lkml
Provides-Extra: test
Requires-Dist: pydantic ; extra == 'test'
Requires-Dist: lkml ; extra == 'test'
